{"nodes": [{"id": "ares_config_py", "label": "config.py", "file_type": "code", "source_file": "ares\\config.py", "source_location": "L1"}, {"id": "config_aressettings", "label": "AresSettings", "file_type": "code", "source_file": "ares\\config.py", "source_location": "L12"}, {"id": "basesettings", "label": "BaseSettings", "file_type": "code", "source_file": "", "source_location": ""}, {"id": "config_parse_keys", "label": "parse_keys()", "file_type": "code", "source_file": "ares\\config.py", "source_location": "L47"}, {"id": "config_merge_legacy_api_key", "label": "merge_legacy_api_key()", "file_type": "code", "source_file": "ares\\config.py", "source_location": "L55"}, {"id": "config_async_database_url", "label": "async_database_url()", "file_type": "code", "source_file": "ares\\config.py", "source_location": "L65"}, {"id": "config_is_sqlite", "label": "is_sqlite()", "file_type": "code", "source_file": "ares\\config.py", "source_location": "L71"}, {"id": "config_load_ares_config", "label": "load_ares_config()", "file_type": "code", "source_file": "ares\\config.py", "source_location": "L75"}, {"id": "config_get_settings", "label": "get_settings()", "file_type": "code", "source_file": "ares\\config.py", "source_location": "L83"}], "edges": [{"source": "ares_config_py", "target": "functools", "relation": "imports_from", "confidence": "EXTRACTED", "source_file": "ares\\config.py", "source_location": "L3", "weight": 1.0}, {"source": "ares_config_py", "target": "pathlib", "relation": "imports_from", "confidence": "EXTRACTED", "source_file": "ares\\config.py", "source_location": "L4", "weight": 1.0}, {"source": "ares_config_py", "target": "typing", "relation": "imports_from", "confidence": "EXTRACTED", "source_file": "ares\\config.py", "source_location": "L5", "weight": 1.0}, {"source": "ares_config_py", "target": "yaml", "relation": "imports", "confidence": "EXTRACTED", "source_file": "ares\\config.py", "source_location": "L7", "weight": 1.0}, {"source": "ares_config_py", "target": "pydantic", "relation": "imports_from", "confidence": "EXTRACTED", "source_file": "ares\\config.py", "source_location": "L8", "weight": 1.0}, {"source": "ares_config_py", "target": "pydantic_settings", "relation": "imports_from", "confidence": "EXTRACTED", "source_file": "ares\\config.py", "source_location": "L9", "weight": 1.0}, {"source": "ares_config_py", "target": "config_aressettings", "relation": "contains", "confidence": "EXTRACTED", "source_file": "ares\\config.py", "source_location": "L12", "weight": 1.0}, {"source": "config_aressettings", "target": "basesettings", "relation": "inherits", "confidence": "EXTRACTED", "source_file": "ares\\config.py", "source_location": "L12", "weight": 1.0}, {"source": "ares_config_py", "target": "config_parse_keys", "relation": "contains", "confidence": "EXTRACTED", "source_file": "ares\\config.py", "source_location": "L47", "weight": 1.0}, {"source": "ares_config_py", "target": "config_merge_legacy_api_key", "relation": "contains", "confidence": "EXTRACTED", "source_file": "ares\\config.py", "source_location": "L55", "weight": 1.0}, {"source": "ares_config_py", "target": "config_async_database_url", "relation": "contains", "confidence": "EXTRACTED", "source_file": "ares\\config.py", "source_location": "L65", "weight": 1.0}, {"source": "ares_config_py", "target": "config_is_sqlite", "relation": "contains", "confidence": "EXTRACTED", "source_file": "ares\\config.py", "source_location": "L71", "weight": 1.0}, {"source": "ares_config_py", "target": "config_load_ares_config", "relation": "contains", "confidence": "EXTRACTED", "source_file": "ares\\config.py", "source_location": "L75", "weight": 1.0}, {"source": "ares_config_py", "target": "config_get_settings", "relation": "contains", "confidence": "EXTRACTED", "source_file": "ares\\config.py", "source_location": "L83", "weight": 1.0}, {"source": "config_get_settings", "target": "config_aressettings", "relation": "calls", "confidence": "EXTRACTED", "source_file": "ares\\config.py", "source_location": "L84", "weight": 1.0}], "raw_calls": [{"caller_nid": "config_parse_keys", "callee": "isinstance", "source_file": "ares\\config.py", "source_location": "L50"}, {"caller_nid": "config_parse_keys", "callee": "strip", "source_file": "ares\\config.py", "source_location": "L51"}, {"caller_nid": "config_parse_keys", "callee": "split", "source_file": "ares\\config.py", "source_location": "L51"}, {"caller_nid": "config_parse_keys", "callee": "strip", "source_file": "ares\\config.py", "source_location": "L51"}, {"caller_nid": "config_parse_keys", "callee": "list", "source_file": "ares\\config.py", "source_location": "L52"}, {"caller_nid": "config_merge_legacy_api_key", "callee": "list", "source_file": "ares\\config.py", "source_location": "L56"}, {"caller_nid": "config_merge_legacy_api_key", "callee": "append", "source_file": "ares\\config.py", "source_location": "L58"}, {"caller_nid": "config_merge_legacy_api_key", "callee": "list", "source_file": "ares\\config.py", "source_location": "L59"}, {"caller_nid": "config_merge_legacy_api_key", "callee": "fromkeys", "source_file": "ares\\config.py", "source_location": "L59"}, {"caller_nid": "config_merge_legacy_api_key", "callee": "ValueError", "source_file": "ares\\config.py", "source_location": "L61"}, {"caller_nid": "config_async_database_url", "callee": "startswith", "source_file": "ares\\config.py", "source_location": "L66"}, {"caller_nid": "config_async_database_url", "callee": "replace", "source_file": "ares\\config.py", "source_location": "L67"}, {"caller_nid": "config_is_sqlite", "callee": "startswith", "source_file": "ares\\config.py", "source_location": "L72"}, {"caller_nid": "config_load_ares_config", "callee": "Path", "source_file": "ares\\config.py", "source_location": "L76"}, {"caller_nid": "config_load_ares_config", "callee": "exists", "source_file": "ares\\config.py", "source_location": "L77"}, {"caller_nid": "config_load_ares_config", "callee": "safe_load", "source_file": "ares\\config.py", "source_location": "L79"}, {"caller_nid": "config_load_ares_config", "callee": "read_text", "source_file": "ares\\config.py", "source_location": "L79"}]}