{"nodes": [{"id": "dashboard_components_connection_status_py", "label": "connection_status.py", "file_type": "code", "source_file": "dashboard\\components\\connection_status.py", "source_location": "L1"}, {"id": "connection_status_ensure_api_connection", "label": "ensure_api_connection()", "file_type": "code", "source_file": "dashboard\\components\\connection_status.py", "source_location": "L11"}], "edges": [{"source": "dashboard_components_connection_status_py", "target": "time", "relation": "imports", "confidence": "EXTRACTED", "source_file": "dashboard\\components\\connection_status.py", "source_location": "L3", "weight": 1.0}, {"source": "dashboard_components_connection_status_py", "target": "streamlit", "relation": "imports", "confidence": "EXTRACTED", "source_file": "dashboard\\components\\connection_status.py", "source_location": "L5", "weight": 1.0}, {"source": "dashboard_components_connection_status_py", "target": "streamlit_components_v1", "relation": "imports", "confidence": "EXTRACTED", "source_file": "dashboard\\components\\connection_status.py", "source_location": "L6", "weight": 1.0}, {"source": "dashboard_components_connection_status_py", "target": "dashboard_api_client", "relation": "imports_from", "confidence": "EXTRACTED", "source_file": "dashboard\\components\\connection_status.py", "source_location": "L8", "weight": 1.0}, {"source": "dashboard_components_connection_status_py", "target": "connection_status_ensure_api_connection", "relation": "contains", "confidence": "EXTRACTED", "source_file": "dashboard\\components\\connection_status.py", "source_location": "L11", "weight": 1.0}], "raw_calls": [{"caller_nid": "connection_status_ensure_api_connection", "callee": "safe_api_call", "source_file": "dashboard\\components\\connection_status.py", "source_location": "L12"}, {"caller_nid": "connection_status_ensure_api_connection", "callee": "get", "source_file": "dashboard\\components\\connection_status.py", "source_location": "L12"}, {"caller_nid": "connection_status_ensure_api_connection", "callee": "title", "source_file": "dashboard\\components\\connection_status.py", "source_location": "L14"}, {"caller_nid": "connection_status_ensure_api_connection", "callee": "error", "source_file": "dashboard\\components\\connection_status.py", "source_location": "L15"}, {"caller_nid": "connection_status_ensure_api_connection", "callee": "caption", "source_file": "dashboard\\components\\connection_status.py", "source_location": "L16"}, {"caller_nid": "connection_status_ensure_api_connection", "callee": "button", "source_file": "dashboard\\components\\connection_status.py", "source_location": "L17"}, {"caller_nid": "connection_status_ensure_api_connection", "callee": "rerun", "source_file": "dashboard\\components\\connection_status.py", "source_location": "L18"}, {"caller_nid": "connection_status_ensure_api_connection", "callee": "html", "source_file": "dashboard\\components\\connection_status.py", "source_location": "L19"}, {"caller_nid": "connection_status_ensure_api_connection", "callee": "sleep", "source_file": "dashboard\\components\\connection_status.py", "source_location": "L29"}, {"caller_nid": "connection_status_ensure_api_connection", "callee": "isinstance", "source_file": "dashboard\\components\\connection_status.py", "source_location": "L31"}, {"caller_nid": "connection_status_ensure_api_connection", "callee": "get", "source_file": "dashboard\\components\\connection_status.py", "source_location": "L31"}, {"caller_nid": "connection_status_ensure_api_connection", "callee": "warning", "source_file": "dashboard\\components\\connection_status.py", "source_location": "L33"}]}