{"nodes": [{"id": "ares_gate_decision_py", "label": "decision.py", "file_type": "code", "source_file": "ares\\gate\\decision.py", "source_location": "L1"}, {"id": "decision_gatedecision", "label": "GateDecision", "file_type": "code", "source_file": "ares\\gate\\decision.py", "source_location": "L7"}], "edges": [{"source": "ares_gate_decision_py", "target": "dataclasses", "relation": "imports_from", "confidence": "EXTRACTED", "source_file": "ares\\gate\\decision.py", "source_location": "L3", "weight": 1.0}, {"source": "ares_gate_decision_py", "target": "decision_gatedecision", "relation": "contains", "confidence": "EXTRACTED", "source_file": "ares\\gate\\decision.py", "source_location": "L7", "weight": 1.0}], "raw_calls": []}