{"nodes": [{"id": "ares_evaluators_detection_py", "label": "detection.py", "file_type": "code", "source_file": "ares\\evaluators\\detection.py", "source_location": "L1"}, {"id": "detection_detectionevaluator", "label": "DetectionEvaluator", "file_type": "code", "source_file": "ares\\evaluators\\detection.py", "source_location": "L6"}, {"id": "classificationevaluator", "label": "ClassificationEvaluator", "file_type": "code", "source_file": "", "source_location": ""}, {"id": "detection_rationale_7", "label": "Scaffold detection evaluator; defaults to classification-style label metrics.", "file_type": "rationale", "source_file": "ares\\evaluators\\detection.py", "source_location": "L7"}], "edges": [{"source": "ares_evaluators_detection_py", "target": "ares_evaluators_classification", "relation": "imports_from", "confidence": "EXTRACTED", "source_file": "ares\\evaluators\\detection.py", "source_location": "L3", "weight": 1.0}, {"source": "ares_evaluators_detection_py", "target": "detection_detectionevaluator", "relation": "contains", "confidence": "EXTRACTED", "source_file": "ares\\evaluators\\detection.py", "source_location": "L6", "weight": 1.0}, {"source": "detection_detectionevaluator", "target": "classificationevaluator", "relation": "inherits", "confidence": "EXTRACTED", "source_file": "ares\\evaluators\\detection.py", "source_location": "L6", "weight": 1.0}, {"source": "detection_rationale_7", "target": "detection_detectionevaluator", "relation": "rationale_for", "confidence": "EXTRACTED", "source_file": "ares\\evaluators\\detection.py", "source_location": "L7", "weight": 1.0}], "raw_calls": []}